CHANGES.txt
README.txt
setup.py
docs/Makefile
docs/api.rst
docs/conf.py
docs/index.rst
docs/narr/appendix.rst
docs/narr/i18n.rst
docs/narr/intro.rst
docs/narr/metal.rst
docs/narr/tal.rst
docs/narr/tales.rst
src/chameleon/__init__.py
src/chameleon.zpt.egg-info/PKG-INFO
src/chameleon.zpt.egg-info/SOURCES.txt
src/chameleon.zpt.egg-info/dependency_links.txt
src/chameleon.zpt.egg-info/namespace_packages.txt
src/chameleon.zpt.egg-info/not-zip-safe
src/chameleon.zpt.egg-info/requires.txt
src/chameleon.zpt.egg-info/top_level.txt